MANIFEST.in
README
setup.py
django_shop_bulkform.egg-info/PKG-INFO
django_shop_bulkform.egg-info/SOURCES.txt
django_shop_bulkform.egg-info/dependency_links.txt
django_shop_bulkform.egg-info/top_level.txt
django_shop_bulkform.egg-info/zip-safe
shop_bulkform/__init__.py
shop_bulkform/models.py
shop_bulkform/urls.py
shop_bulkform/views.py