Metadata-Version: 1.0
Name: django-shop-bulkform
Version: 0.1.0
Summary: A bulk order form for a django-shop site.
Home-page: http://github.com/powellc/django-shop-bulkform
Author: Colin Powell
Author-email: colin@onecardinal.com
License: BSD
Download-URL: http://github.com/powellc/django-shop-bulkform/downloads
Platform: UNKNOWN
Classifier: Development Status :: 4 - Beta
Classifier: Environment :: Web Environment
Classifier: Intended Audience :: Developers
Classifier: License :: OSI Approved :: BSD License
Classifier: Operating System :: OS Independent
Classifier: Programming Language :: Python
Classifier: Framework :: Django
